{
  "id": 1757656859609,
  "isim": "DENEME3",
  "not": "",
  "arsiv": false,
  "haftalar": [
    {
      "haftaNo": 5,
      "baslangic": "2025-08-11",
      "bitis": "2025-08-17",
      "aciklama": "",
      "pdf": null,
      "pdfName": "HATİCE OKTAŞ 11-17 AĞUSTOS 5. HAFTA.pdf",
      "pdfOrijinalIsim": "HATİCE OKTAŞ 11-17 AĞUSTOS 5. HAFTA.pdf",
      "pdfYolu": "pdfs/HATİCE OKTAŞ 11-17 AĞUSTOS 5. HAFTA.pdf",
      "githubUrl": "https://github.com/mustafasacar35/lipodem-takip-paneli-2/blob/main/pdfs/HATİCE OKTAŞ 11-17 AĞUSTOS 5. HAFTA.pdf",
      "indirmeUrl": "https://raw.githubusercontent.com/mustafasacar35/lipodem-takip-paneli-2/main/pdfs/HATİCE OKTAŞ 11-17 AĞUSTOS 5. HAFTA.pdf",
      "kayitTarihi": "2025-09-12T07:30:41.206Z",
      "tarifKartlar": [
        {
          "tarifAdi": "bonfile steak",
          "kartResmi": "bonfile_steak.jpg",
          "kartData": "https://mustafasacar35.github.io/lipodem-takip-paneli-2/tarifler/bonfile_steak.jpg",
          "eslesmeTuru": "tam eşleşme"
        },
        {
          "tarifAdi": "peynirli biber dolması",
          "kartResmi": "peynirli_biber_dolmasi.jpg",
          "kartData": "https://mustafasacar35.github.io/lipodem-takip-paneli-2/tarifler/peynirli_biber_dolmasi.jpg",
          "eslesmeTuru": "tam eşleşme"
        },
        {
          "tarifAdi": "haşhaş ezmesi ekmeği (1 dilim)",
          "kartResmi": "hashas_ezmesi_ekmegi.jpg",
          "kartData": "https://mustafasacar35.github.io/lipodem-takip-paneli-2/tarifler/hashas_ezmesi_ekmegi.jpg",
          "eslesmeTuru": "tam eşleşme"
        },
        {
          "tarifAdi": "göçmen salatası",
          "kartResmi": "gocmen_salatasi.jpg",
          "kartData": "https://mustafasacar35.github.io/lipodem-takip-paneli-2/tarifler/gocmen_salatasi.jpg",
          "eslesmeTuru": "tam eşleşme"
        },
        {
          "tarifAdi": "cevizli kaşık salatası",
          "kartResmi": "cevizli_kasik_salatasi.jpg",
          "kartData": "https://mustafasacar35.github.io/lipodem-takip-paneli-2/tarifler/cevizli_kasik_salatasi.jpg",
          "eslesmeTuru": "tam eşleşme"
        },
        {
          "tarifAdi": "lupin unlu poğaça (veya 3 adet lorlu poğaça)",
          "kartResmi": "lupin_unlu_pogaca.jpg",
          "kartData": "https://mustafasacar35.github.io/lipodem-takip-paneli-2/tarifler/lupin_unlu_pogaca.jpg",
          "eslesmeTuru": "tam eşleşme"
        },
        {
          "tarifAdi": "kıymalı kabak/ bamya yemeği",
          "kartResmi": "kiymali_kabak_yemegi.jpg",
          "kartData": "https://mustafasacar35.github.io/lipodem-takip-paneli-2/tarifler/kiymali_kabak_yemegi.jpg",
          "eslesmeTuru": "manuel eşleştirme"
        },
        {
          "tarifAdi": "yoğurtlu salatalık mezesi",
          "kartResmi": "yogurtlu_salatalik_mezesi.jpg",
          "kartData": "https://mustafasacar35.github.io/lipodem-takip-paneli-2/tarifler/yogurtlu_salatalik_mezesi.jpg",
          "eslesmeTuru": "tam eşleşme"
        },
        {
          "tarifAdi": "yumurtalı ıspanak / pazı kavurma",
          "kartResmi": "yumurtali_ispanak.jpg",
          "kartData": "https://mustafasacar35.github.io/lipodem-takip-paneli-2/tarifler/yumurtali_ispanak.jpg",
          "eslesmeTuru": "tam eşleşme"
        },
        {
          "tarifAdi": "alinazik kebabı",
          "kartResmi": "alinazik_kebabi.jpg",
          "kartData": "https://mustafasacar35.github.io/lipodem-takip-paneli-2/tarifler/alinazik_kebabi.jpg",
          "eslesmeTuru": "tam eşleşme"
        }
      ],
      "tarifler": [
        "pazartesi̇",
        "öğle (tercihen saat 12:00 civarında)",
        "haşlanmış yumurta (1 adet) + (üzerine eritilmiş 1 tatlı kaşığı tereyağı ve istenilen baharatlar",
        "zeytin (5 adet)",
        "3 cherry domatesi bir yemek kaşığı zeytinyağı ile soteleyip, üzerine kekik ve pul biber serpin",
        "tulum / kaşar peyniri (30 gram)",
        "akşam (tercihen hava kararınca)",
        "bonfile steak",
        "yeşil salata (mevsim yeşillikleri+ 1 tatlı kaşığı zeytinyağı)",
        "ev yapımı turşu",
        "kabak çekirdeği (1 avuç)",
        "kollajen (1 ölçek 10 gram)",
        "sali",
        "öğle (tercihen saat 12:00 civarında)",
        "mantarlı omlet (1 adet yumurta,5 adet mantar,1 tatlı kaşığı tereyağı)",
        "tulum peyniri veya kaşar peyniri (30 gram)",
        "yeşillikler (dereotu, roka, maydanoz, marul vs. + sirke, limon ve 1 yemek kaşığı zeytinyağı ile)",
        "bitter çikolata (2 kare)",
        "fındık (10 adet)",
        "akşam (tercihen hava kararınca)",
        "ızgara ya da fırında balık (çupra, levrek, alabalık vs.)",
        "semizotu salatası (2 avuç semizotu,1 adet orta boy domates,1 adet salatalık,1 adet biber ve 1 yemek kaşığı",
        "ceviz (3 adet)",
        "çarşamba",
        "öğle (tercihen saat 12:00 civarında)",
        "peynirli biber dolması",
        "haşhaş ezmesi ekmeği (1 dilim)",
        "cherry domates (2 adet)",
        "yeşillikler (dereotu, roka, maydanoz + 1 yemek kaşığı zeytinyağı)",
        "ceviz (5 adet)",
        "zeytin (10 adet)",
        "akşam (tercihen hava kararınca)",
        "haşlanmış tavuk göğsü (istenilen baharatlarla karıştırıp roka salatasının üzerine koyalım)",
        "roka salatası (yarım bağ roka, 1 adet küçük salatalık, 3 adet cherry domates, yarım kırmızı soğan + limon, 1 yemek",
        "fındık (10 adet)",
        "kollajen (1 ölçek 10 gram)",
        "perşembe",
        "öğle (tercihen saat 12:00 civarında)",
        "haşlanmış yumurta (1 adet)",
        "tulum / kaşar peyniri (30 gram)",
        "zeytin (5 adet)",
        "salatalık (orta boy) ,cherry domates (2 adet), 4-5 dal roka, 4-5 dal tere, 2 adet küçük yeşil biber",
        "ceviz (3 adet)",
        "akşam (tercihen hava kararınca)",
        "köfte",
        "göçmen salatası",
        "cuma",
        "öğle (tercihen saat 12:00 civarında)",
        "sahanda yumurta (1 yumurta – 1 yemek kaşığı tereyağı)",
        "yeşillikler (dereotu, roka, maydanoz, marul vs. + sirke, limon ile)",
        "tulum / kaşar peyniri (30 gram)",
        "zeytin (10 adet)",
        "haşhaş ezmesi ekmeği (1 dilim)",
        "salatalık (orta boy) + cherry domates (2 adet)",
        "akşam (tercihen hava kararınca)",
        "tavuk pirzola ya da kanat",
        "cevizli kaşık salatası",
        "turşu (organik, ev yapımı)",
        "kabak çekirdeği (1 avuç)",
        "cumartesi̇",
        "öğle (tercihen saat 12:00 civarında)",
        "lupin unlu poğaça (veya 3 adet lorlu poğaça)",
        "yeşillikler (4 yaprak marul, 4-5 yaprak roka, 1 adet küçük salatalık, limon ve sirke+1 yemek kaşığı zeytinyağı ile)",
        "zeytin (10 adet)",
        "tulum / kaşar peyniri (30 gram)",
        "akşam (tercihen hava kararınca)",
        "kıymalı kabak/ bamya yemeği",
        "yoğurtlu salatalık mezesi",
        "pazar",
        "öğle (tercihen saat 12:00 civarında)",
        "yumurtalı ıspanak / pazı kavurma",
        "zeytin (10 adet)",
        "salatalık (orta boy) + cherry domates (2 adet)+ 4-5 dal maydanoz+ 2 adet küçük yeşil biber",
        "tulum peyniri (50 gram)",
        "bitter çikolata (2 kare)",
        "akşam (tercihen hava kararınca)",
        "alinazik kebabı",
        "yeşil salata (marul, dereotu, roka, kırmızı lahana, 1 tatlı kaşığı zeytinyağı)",
        "haşhaş ezmesi ekmeği (1 dilim)",
        "turşu (organik, ev yapımı)",
        "ara öğün (tercihen saat 15:00-16:00 civarında): maden suyu (2 çimdik kaya tuzu ve limon 5-10 damla limon",
        "günlük ortalama 5000 adım önerilir",
        "günlük su tüketimi 2 litrenin üzerinde olması önerilir"
      ],
      "gptMesaj": "",
      "kilitli": false,
      "ozelTabFormat": false,
      "pdfFile": {},
      "manuelKartlar": [],
      "eslesenTarifler": [
        "bonfile steak",
        "peynirli biber dolması",
        "haşhaş ezmesi ekmeği (1 dilim)",
        "göçmen salatası",
        "haşhaş ezmesi ekmeği (1 dilim)",
        "cevizli kaşık salatası",
        "lupin unlu poğaça (veya 3 adet lorlu poğaça)",
        "kıymalı kabak/ bamya yemeği",
        "yoğurtlu salatalık mezesi",
        "yumurtalı ıspanak / pazı kavurma",
        "alinazik kebabı",
        "haşhaş ezmesi ekmeği (1 dilim)"
      ]
    }
  ],
  "olusturmaTarihi": "2025-09-12T06:00:59.609Z",
  "yeniSistem": true,
  "sonGuncelleme": "2025-09-12T07:30:47.849Z",
  "githubKaydedildi": true
}